setup.py
tian/__init__.py
tian/roll.py
tian/roller.py
tian.egg-info/PKG-INFO
tian.egg-info/SOURCES.txt
tian.egg-info/dependency_links.txt
tian.egg-info/not-zip-safe
tian.egg-info/top_level.txt