Metadata-Version: 1.0
Name: tian
Version: 0.1
Summary: A dice parser package
Home-page: http://github.com/QuinnStevens/tian
Author: Quinn Stevens
Author-email: quinn.ng.stevens@gmail.com
License: UNKNOWN
Platform: UNKNOWN
